pytest_nogarbage.py
pytest_nogarbage-1.0.1.dist-info/LICENSE
pytest_nogarbage-1.0.1.dist-info/METADATA
pytest_nogarbage-1.0.1.dist-info/WHEEL
pytest_nogarbage-1.0.1.dist-info/entry_points.txt
pytest_nogarbage-1.0.1.dist-info/top_level.txt
pytest_nogarbage-1.0.1.dist-info/RECORD
